slimevolleygym/__init__.py
slimevolleygym/mlp.py
slimevolleygym/slimevolley.py
slimevolleygym-0.1.0.dist-info/LICENSE
slimevolleygym-0.1.0.dist-info/METADATA
slimevolleygym-0.1.0.dist-info/WHEEL
slimevolleygym-0.1.0.dist-info/top_level.txt
slimevolleygym-0.1.0.dist-info/RECORD
