Metadata-Version: 2.1
Name: slimevolleygym
Version: 0.1.0
Summary: Slime Volleyball Gym Environment
Home-page: https://github.com/hardmaru/slimevolleygym
Author: UNKNOWN
Author-email: UNKNOWN
License: UNKNOWN
Keywords: games,environment,agent,rl,ai,gym
Platform: UNKNOWN
Requires-Dist: gym (>=0.9.4)
Requires-Dist: numpy (>=1.13.0)
